server/__init__.py
server/server.py
server/common/__init__.py
server/common/decos.py
server/common/descryptors.py
server/common/errors.py
server/common/metaclasses.py
server/common/utils.py
server/common/variables.py
server/logs/__init__.py
server/logs/config_client_log.py
server/logs/config_server_log.py
server/server/__init__.py
server/server/add_user.py
server/server/config_window.py
server/server/core.py
server/server/database.py
server/server/main_window.py
server/server/remove_user.py
server/server/server_gui.py
server/server/stat_window.py
server/server/server_models/ActiveUsers.py
server/server/server_models/AllUsers.py
server/server/server_models/Base.py
server/server/server_models/LoginHistory.py
server/server/server_models/UsersContacts.py
server/server/server_models/UsersHistory.py
server/server/server_models/__init__.py
server/unit_tests/__init__.py
server/unit_tests/test_client.py
server/unit_tests/test_utils.py
server_chat_pyqt_dax-0.0.1.dist-info/METADATA
server_chat_pyqt_dax-0.0.1.dist-info/WHEEL
server_chat_pyqt_dax-0.0.1.dist-info/top_level.txt
server_chat_pyqt_dax-0.0.1.dist-info/RECORD
