Metadata-Version: 2.1
Name: server-chat-pyqt-dax
Version: 0.0.1
Summary: Server packet
Author: Evgeniy Gorbunov
Author-email: test@mail.ru
